i2/__init__.py
i2/_deprecated.py
i2/base.py
i2/castgraph.py
i2/chain_map.py
i2/deco.py
i2/doc_mint.py
i2/errors.py
i2/footprints.py
i2/io_trans.py
i2/itypes.py
i2/key_path.py
i2/multi_object.py
i2/routing_forest.py
i2/signatures.py
i2/util.py
i2/wrapper.py
i2/examples/__init__.py
i2/examples/castgraph_examples.py
i2/examples/signature_calculus.py
i2/scrap/__init__.py
i2/scrap/scrap.py
i2/scrap/scrap_ch_variadics.py
i2/scrap/scrap_kwargs.py
i2/scrap/signature_bops.py
i2/scrap/simple_pymint.py
i2/scrap/switch_case_tree.py
i2/tests/__init__.py
i2/tests/footprints_test.py
i2/tests/objects_for_testing.py
i2/tests/test_castgraph.py
i2/tests/test_castgraph_kinds.py
i2/tests/test_signatures.py
i2/tests/test_util.py
i2/tests/test_wrapper.py
i2/tests/util.py
i2-0.1.60.dist-info/licenses/LICENSE
i2-0.1.60.dist-info/METADATA
i2-0.1.60.dist-info/WHEEL
i2-0.1.60.dist-info/top_level.txt
i2-0.1.60.dist-info/RECORD
