Metadata-Version: 2.4
Name: i2
Version: 0.1.60
Summary: The middleware toolbox
Home-page: https://github.com/i2mint/i2
License: Apache Software License
Platform: any
License-File: LICENSE
Provides-Extra: testing
Dynamic: license-file
